decopatch/__init__.py
decopatch/_version.py
decopatch/main.py
decopatch/main.pyi
decopatch/py.typed
decopatch/utils_calls.py
decopatch/utils_disambiguation.py
decopatch/utils_modes.py
decopatch-1.4.10.dist-info/LICENSE
decopatch-1.4.10.dist-info/METADATA
decopatch-1.4.10.dist-info/WHEEL
decopatch-1.4.10.dist-info/top_level.txt
decopatch-1.4.10.dist-info/RECORD
