Metadata-Version: 2.1
Name: decopatch
Version: 1.4.10
Summary: Create decorators easily in python.
Home-page: https://github.com/smarie/python-decopatch
Author: Sylvain MARIE <sylvain.marie@se.com>
Maintainer: Sylvain MARIE <sylvain.marie@se.com>
License: BSD 3-Clause
Download-URL: https://github.com/smarie/python-decopatch/tarball/1.4.10
Keywords: decorate decorator function class parenthesis generate generation define definition signature args wrapper wraps auto easy preserve
Platform: UNKNOWN
Classifier: Development Status :: 5 - Production/Stable
Classifier: Intended Audience :: Developers
Classifier: License :: OSI Approved :: BSD License
Classifier: Topic :: Software Development :: Libraries :: Python Modules
Classifier: Programming Language :: Python
Classifier: Programming Language :: Python :: 2
Classifier: Programming Language :: Python :: 2.7
Classifier: Programming Language :: Python :: 3
Classifier: Programming Language :: Python :: 3.5
Classifier: Programming Language :: Python :: 3.6
Classifier: Programming Language :: Python :: 3.7
Classifier: Programming Language :: Python :: 3.8
Classifier: Programming Language :: Python :: 3.9
License-File: LICENSE
